AUTHORS
COPYING
MANIFEST.in
README.md
pyproject.toml
setup.py
omega/__init__.py
omega/astimage.py
omega/base.py
omega/ceaproj.py
omega/gtk3.py
omega/ipynb.py
omega/jupyter.py
omega/latex.py
omega/layout.py
omega/pango_g3.py
omega/pyrapimage.py
omega/pywcs.py
omega/rect.py
omega/render.py
omega/sinproj.py
omega/sphere.py
omega/stamps.py
omega/styles.py
omega/util.py
omegaplot.egg-info/PKG-INFO
omegaplot.egg-info/SOURCES.txt
omegaplot.egg-info/dependency_links.txt
omegaplot.egg-info/entry_points.txt
omegaplot.egg-info/not-zip-safe
omegaplot.egg-info/requires.txt
omegaplot.egg-info/top_level.txt
oputil/__init__.py
oputil/contourgrid.py
oputil/latexsnippet.py
oputil/omegafig.py
oputil/omegamap.py